mnt/WorkSpace/code/protocols_builder/LICENSE
mnt/WorkSpace/code/protocols_builder/README.md
pyalgotrader_protocols/__init__.py
pyalgotrader_protocols/algorithm.py
pyalgotrader_protocols/broker.py
pyalgotrader_protocols/broker_manager.py
pyalgotrader_protocols/chart.py
pyalgotrader_protocols/data.py
pyalgotrader_protocols/data_manager.py
pyalgotrader_protocols/feed.py
pyalgotrader_protocols/indicator.py
pyalgotrader_protocols/store.py
pyalgotrader_protocols/strategy.py
pyalgotrader_protocols/symbol.py
pyalgotrader_protocols-0.0.3.dist-info/LICENSE
pyalgotrader_protocols-0.0.3.dist-info/METADATA
pyalgotrader_protocols-0.0.3.dist-info/WHEEL
pyalgotrader_protocols-0.0.3.dist-info/top_level.txt
pyalgotrader_protocols-0.0.3.dist-info/RECORD
