Metadata-Version: 2.1
Name: pyalgotrader-protocols
Version: 0.0.3
Summary: PyAlgoTrader Protocols
Home-page: https://github.com/krunaldodiya/pyalgotrader-protocols
Author: Krunal Dodiya
Author-email: kunal.dodiya1@gmail.com
Classifier: Programming Language :: Python :: 3
Classifier: Operating System :: OS Independent
License-File: LICENSE
Requires-Dist: requests
